omniblack/vulcan/Caddyfile.json
omniblack/vulcan/__init__.py
omniblack/vulcan/__main__.py
omniblack/vulcan/app.py
omniblack/vulcan/appProvider.js
omniblack/vulcan/build.js
omniblack/vulcan/createConfig.js
omniblack/vulcan/dev.js
omniblack/vulcan/dev.py
omniblack/vulcan/files.js
omniblack/vulcan/findApps.js
omniblack/vulcan/kube.py
omniblack/vulcan/logger.js
omniblack/vulcan/mergeRollup.js
omniblack/vulcan/model.py
omniblack/vulcan/nodejs_kube.yaml
omniblack/vulcan/reporter.js
omniblack/vulcan/start.py
omniblack/vulcan/styles.js
omniblack/vulcan/template.html
omniblack/vulcan/configs/__init__.py
omniblack/vulcan/configs/base.js
omniblack/vulcan/configs/dev.js
omniblack/vulcan/configs/lib.js
omniblack/vulcan/configs/spa.js
omniblack/vulcan/configs/utils.js
omniblack.vulcan-0.1.0.dist-info/LICENSE.txt
omniblack.vulcan-0.1.0.dist-info/METADATA
omniblack.vulcan-0.1.0.dist-info/WHEEL
omniblack.vulcan-0.1.0.dist-info/entry_points.txt
omniblack.vulcan-0.1.0.dist-info/top_level.txt
omniblack.vulcan-0.1.0.dist-info/RECORD
