Metadata-Version: 2.1
Name: omniblack.vulcan
Version: 0.1.0
Summary: A tool for managing mono-repos.
Author-email: Terry Patterson <Terryp@wegrok.net>
License: 
Project-URL: Homepage, https://gitlab.com/terryp/terry/-/tree/next/tooling/vulcan
Project-URL: Repository, https://gitlab.com/terryp/terry.git
Requires-Python: ~=3.9
License-File: LICENSE.txt
Requires-Dist: omniblack.caddy
Requires-Dist: omniblack.cli
Requires-Dist: omniblack.model
Requires-Dist: omniblack.repo
Requires-Dist: pathspec ~=0.8
Requires-Dist: sh
Requires-Dist: rich
